waddle/__main__.py
waddle/argparse.py
waddle/argparse_test.py
waddle/config.py
waddle/metadata.py
waddle/metadata_test.py
waddle/processor.py
waddle/utils.py
waddle/utils_test.py
waddle/audios/align_offset.py
waddle/audios/align_offset_test.py
waddle/audios/call_tools.py
waddle/audios/call_tools_test.py
waddle/audios/clip.py
waddle/audios/clip_test.py
waddle/audios/enhancer.py
waddle/audios/enhancer_test.py
waddle/audios/split_quiet.py
waddle/audios/split_quiet_test.py
waddle/processing/combine.py
waddle/processing/segment.py
waddle/processing/segment_test.py
waddle/processing/combine_tests/audio_files_test.py
waddle/processing/combine_tests/segments_test.py
waddle/processing/combine_tests/srt_test.py
waddle/processing/combine_tests/timeline_test.py
waddle/tools/install_all_tools.py
waddle/tools/install_deep_filter.py
waddle/tools/install_whisper_cpp.py
waddle_ai-0.1.5.dist-info/METADATA
waddle_ai-0.1.5.dist-info/WHEEL
waddle_ai-0.1.5.dist-info/entry_points.txt
waddle_ai-0.1.5.dist-info/licenses/LICENSE
waddle_ai-0.1.5.dist-info/RECORD
