Metadata-Version: 2.4
Name: waddle-ai
Version: 0.1.5
Summary: A podcast preprocessing library for aligning, normalizing, and transcribing audio files.
Author-email: Masamune Ishihara <mwishiha@ucsc.edu>, Shun Kashiwa <skashiwa@ucsd.edu>
License: MIT
License-File: LICENSE
Classifier: Development Status :: 4 - Beta
Classifier: Environment :: Console
Classifier: Intended Audience :: Developers
Classifier: License :: OSI Approved :: MIT License
Classifier: Operating System :: OS Independent
Classifier: Programming Language :: Python :: 3
Classifier: Programming Language :: Python :: 3.13
Classifier: Topic :: Multimedia :: Sound/Audio
Classifier: Topic :: Multimedia :: Sound/Audio :: Analysis
Classifier: Topic :: Multimedia :: Sound/Audio :: Speech
Classifier: Topic :: Scientific/Engineering :: Artificial Intelligence
Classifier: Topic :: Utilities
Requires-Python: >=3.13
Requires-Dist: librosa>=0.11.0
Requires-Dist: mutagen>=1.47.0
Requires-Dist: numba>=0.61.2
Requires-Dist: numpy>=2.0.0
Requires-Dist: platformdirs>=4.3.6
Requires-Dist: pydub>=0.25.1
Requires-Dist: soundfile>=0.12.1
Requires-Dist: tqdm>=4.67.1
